MANIFEST.in
README.md
requirements.txt
setup.cfg
setup.py
Flask_Boto3.egg-info/PKG-INFO
Flask_Boto3.egg-info/SOURCES.txt
Flask_Boto3.egg-info/dependency_links.txt
Flask_Boto3.egg-info/not-zip-safe
Flask_Boto3.egg-info/requires.txt
Flask_Boto3.egg-info/top_level.txt
flask_boto3/__init__.py