Metadata-Version: 1.1
Name: Flask-Boto3
Version: 0.3.2
Summary: Flask extension that ties boto3 to the application
Home-page: https://github.com/Ketouem/flask-boto3
Author: Cyril "Ketouem" Thomas
Author-email: ketouem@gmail.com
License: MIT
Platform: any
Classifier: Environment :: Web Environment
Classifier: Intended Audience :: Developers
Classifier: License :: OSI Approved :: MIT License
Classifier: Operating System :: OS Independent
Classifier: Programming Language :: Python :: 3.6
Classifier: Topic :: Internet :: WWW/HTTP :: Dynamic Content
Classifier: Topic :: Software Development :: Libraries :: Python Modules
